textpack/__init__.py
textpack/tp.py
textpack2-0.1.3.dist-info/LICENSE
textpack2-0.1.3.dist-info/METADATA
textpack2-0.1.3.dist-info/WHEEL
textpack2-0.1.3.dist-info/top_level.txt
textpack2-0.1.3.dist-info/RECORD
