Metadata-Version: 2.1
Name: textpack2
Version: 0.1.3
Summary: Quickly identify and group similar text strings in a large dataset
Home-page: https://github.com/xelixdev/textpack
Author: Luke Whyte
Author-email: lukeawhyte@gmail.com
Maintainer: Mikuláš Poul
Maintainer-email: mikulaspoul@gmail.com
Classifier: Programming Language :: Python :: 3
Classifier: License :: OSI Approved :: MIT License
Classifier: Operating System :: OS Independent
License-File: LICENSE
Requires-Dist: pandas
Requires-Dist: scikit-learn
Requires-Dist: scipy
Requires-Dist: numpy
Requires-Dist: cython
Requires-Dist: sparse-dot-topn
